gptbuilder/__init__.py
gptbuilder/api.py
gptbuilder/logger.py
gptbuilder/utils.py
gptbuilder/builder/__init__.py
gptbuilder/builder/jsonbuilder.py
gptbuilder/builder/listbuilder.py
gptbuilder/config/__init__.py
gptbuilder/config/config.py
gptbuilder-1.0.2.dist-info/METADATA
gptbuilder-1.0.2.dist-info/WHEEL
gptbuilder-1.0.2.dist-info/top_level.txt
gptbuilder-1.0.2.dist-info/RECORD
